pint_mtools/__init__.py
pint_mtools/babel_names.py
pint_mtools/constants_en.txt
pint_mtools/context.py
pint_mtools/converters.py
pint_mtools/default_en.txt
pint_mtools/default_en_0.6.txt
pint_mtools/definitions.py
pint_mtools/errors.py
pint_mtools/formatting.py
pint_mtools/matplotlib.py
pint_mtools/measurement.py
pint_mtools/pint_eval.py
pint_mtools/quantity.py
pint_mtools/registry.py
pint_mtools/registry_helpers.py
pint_mtools/systems.py
pint_mtools/unit.py
pint_mtools/util.py
pint_mtools/xtranslated.txt
pint_mtools/compat/__init__.py
pint_mtools/compat/chainmap.py
pint_mtools/compat/lrucache.py
pint_mtools/compat/meta.py
pint_mtools/compat/tokenize.py
pint_mtools/testsuite/__init__.py
pint_mtools/testsuite/helpers.py
pint_mtools/testsuite/parameterized.py
pint_mtools/testsuite/test_babel.py
pint_mtools/testsuite/test_contexts.py
pint_mtools/testsuite/test_converters.py
pint_mtools/testsuite/test_definitions.py
pint_mtools/testsuite/test_errors.py
pint_mtools/testsuite/test_formatter.py
pint_mtools/testsuite/test_infer_base_unit.py
pint_mtools/testsuite/test_issues.py
pint_mtools/testsuite/test_measurement.py
pint_mtools/testsuite/test_numpy.py
pint_mtools/testsuite/test_pint_eval.py
pint_mtools/testsuite/test_pitheorem.py
pint_mtools/testsuite/test_quantity.py
pint_mtools/testsuite/test_systems.py
pint_mtools/testsuite/test_umath.py
pint_mtools/testsuite/test_unit.py
pint_mtools/testsuite/test_util.py
pint_mtools-0.12.3.dist-info/AUTHORS
pint_mtools-0.12.3.dist-info/LICENSE
pint_mtools-0.12.3.dist-info/METADATA
pint_mtools-0.12.3.dist-info/WHEEL
pint_mtools-0.12.3.dist-info/top_level.txt
pint_mtools-0.12.3.dist-info/zip-safe
pint_mtools-0.12.3.dist-info/RECORD
